{
  "name": "clojure-lsp",
  "full_name": "clojure-lsp",
  "tap": "homebrew/core",
  "oldname": null,
  "aliases": [

  ],
  "versioned_formulae": [

  ],
  "desc": "Language Server (LSP) for Clojure",
  "license": "MIT",
  "homepage": "https://github.com/clojure-lsp/clojure-lsp",
  "versions": {
    "stable": "20210413T124733",
    "head": "HEAD",
    "bottle": true
  },
  "urls": {
    "stable": {
      "url": "https://github.com/clojure-lsp/clojure-lsp.git",
      "tag": "2021.04.13-12.47.33",
      "revision": "664ced940729d048d3ae11c5a71f03e101d6301f"
    }
  },
  "revision": 0,
  "version_scheme": 0,
  "bottle": {
    "stable": {
      "rebuild": 0,
      "root_url": "https://ghcr.io/v2/linuxbrew/core",
      "files": {
        "arm64_big_sur": {
          "cellar": ":any_skip_relocation",
          "url": "https://ghcr.io/v2/linuxbrew/core/clojure-lsp/blobs/sha256:1719036a888d52fa386d7ea32f573ffc043a6cf707b49881a5ffb9649a58fab7",
          "sha256": "1719036a888d52fa386d7ea32f573ffc043a6cf707b49881a5ffb9649a58fab7"
        },
        "big_sur": {
          "cellar": ":any_skip_relocation",
          "url": "https://ghcr.io/v2/linuxbrew/core/clojure-lsp/blobs/sha256:970d2e9d03e51e3ea1a99d11405ea211af5181ebd28eb7a2a7cb51ea1c27c35e",
          "sha256": "970d2e9d03e51e3ea1a99d11405ea211af5181ebd28eb7a2a7cb51ea1c27c35e"
        },
        "catalina": {
          "cellar": ":any_skip_relocation",
          "url": "https://ghcr.io/v2/linuxbrew/core/clojure-lsp/blobs/sha256:95ec5014d85d5f09e97c6193fd6aeff1ea7c29141277a1c553005582e86e3af7",
          "sha256": "95ec5014d85d5f09e97c6193fd6aeff1ea7c29141277a1c553005582e86e3af7"
        },
        "mojave": {
          "cellar": ":any_skip_relocation",
          "url": "https://ghcr.io/v2/linuxbrew/core/clojure-lsp/blobs/sha256:0fbb4c3ee8f634ff495637461bfc30128322a3004022c2f5432b5c507925fe69",
          "sha256": "0fbb4c3ee8f634ff495637461bfc30128322a3004022c2f5432b5c507925fe69"
        }
      }
    }
  },
  "keg_only": false,
  "bottle_disabled": false,
  "options": [

  ],
  "build_dependencies": [
    "clojure"
  ],
  "dependencies": [
    "openjdk@11"
  ],
  "recommended_dependencies": [

  ],
  "optional_dependencies": [

  ],
  "uses_from_macos": [

  ],
  "requirements": [

  ],
  "conflicts_with": [

  ],
  "caveats": null,
  "installed": [

  ],
  "linked_keg": null,
  "pinned": false,
  "outdated": false,
  "deprecated": false,
  "deprecation_date": null,
  "deprecation_reason": null,
  "disabled": false,
  "disable_date": null,
  "disable_reason": null
}
