{
  "name": "clojure-lsp",
  "full_name": "clojure-lsp",
  "tap": "homebrew/core",
  "oldname": null,
  "aliases": [

  ],
  "versioned_formulae": [

  ],
  "desc": "Language Server (LSP) for Clojure",
  "license": "MIT",
  "homepage": "https://github.com/clojure-lsp/clojure-lsp",
  "versions": {
    "stable": "20210324T004155",
    "head": "HEAD",
    "bottle": true
  },
  "urls": {
    "stable": {
      "url": "https://github.com/clojure-lsp/clojure-lsp.git",
      "tag": "2021.03.24-00.41.55",
      "revision": "3cf38b47c953f7e21d535df4cb91a71a36f03d09"
    }
  },
  "revision": 0,
  "version_scheme": 0,
  "bottle": {
    "stable": {
      "rebuild": 0,
      "cellar": "/home/linuxbrew/.linuxbrew/Cellar",
      "prefix": "/home/linuxbrew/.linuxbrew",
      "root_url": "https://linuxbrew.bintray.com/bottles",
      "files": {
        "arm64_big_sur": {
          "url": "https://linuxbrew.bintray.com/bottles/clojure-lsp-20210324T004155.arm64_big_sur.bottle.tar.gz",
          "sha256": "714620021f25ee83e39040f14bd58b7a4d1f94ef57e5ce9de737539fb50964e1"
        },
        "big_sur": {
          "url": "https://linuxbrew.bintray.com/bottles/clojure-lsp-20210324T004155.big_sur.bottle.tar.gz",
          "sha256": "115564a76c5f8b45e487c0648bbac13a77973137d1ac7fbcdd673c18033c9c25"
        },
        "catalina": {
          "url": "https://linuxbrew.bintray.com/bottles/clojure-lsp-20210324T004155.catalina.bottle.tar.gz",
          "sha256": "352d8a0f6581fc9e56e7ec103f716f966995eeb2d0d9a2065bf4b4fcb9630160"
        },
        "mojave": {
          "url": "https://linuxbrew.bintray.com/bottles/clojure-lsp-20210324T004155.mojave.bottle.tar.gz",
          "sha256": "d1e46a6739dbc18dd5366855a5de4a2bf55957f453bbc70b5a38b768c845c833"
        }
      }
    }
  },
  "keg_only": false,
  "bottle_disabled": false,
  "options": [

  ],
  "build_dependencies": [
    "clojure"
  ],
  "dependencies": [
    "openjdk@11"
  ],
  "recommended_dependencies": [

  ],
  "optional_dependencies": [

  ],
  "uses_from_macos": [

  ],
  "requirements": [

  ],
  "conflicts_with": [

  ],
  "caveats": null,
  "installed": [

  ],
  "linked_keg": null,
  "pinned": false,
  "outdated": false,
  "deprecated": false,
  "deprecation_date": null,
  "deprecation_reason": null,
  "disabled": false,
  "disable_date": null,
  "disable_reason": null
}
