{
  "name": "cmus",
  "full_name": "cmus",
  "oldname": null,
  "aliases": [

  ],
  "versioned_formulae": [

  ],
  "desc": "Music player with an ncurses based interface",
  "license": "GPL-2.0",
  "homepage": "https://cmus.github.io/",
  "versions": {
    "stable": "2.8.0",
    "head": "HEAD",
    "bottle": true
  },
  "urls": {
    "stable": {
      "url": "https://github.com/cmus/cmus/archive/v2.8.0.tar.gz",
      "tag": null,
      "revision": null
    }
  },
  "revision": 3,
  "version_scheme": 0,
  "bottle": {
    "stable": {
      "rebuild": 0,
      "cellar": "/home/linuxbrew/.linuxbrew/Cellar",
      "prefix": "/home/linuxbrew/.linuxbrew",
      "root_url": "https://linuxbrew.bintray.com/bottles",
      "files": {
        "catalina": {
          "url": "https://linuxbrew.bintray.com/bottles/cmus-2.8.0_3.catalina.bottle.tar.gz",
          "sha256": "28bcd80ed26797cfbf1d7e0b42da105fcf431e8ddf268410a9d48def8c5c9b6b"
        },
        "mojave": {
          "url": "https://linuxbrew.bintray.com/bottles/cmus-2.8.0_3.mojave.bottle.tar.gz",
          "sha256": "04bb64db2401fc5007bbb82746676c789ef33d83415a7d56235ded3983bb0e12"
        },
        "high_sierra": {
          "url": "https://linuxbrew.bintray.com/bottles/cmus-2.8.0_3.high_sierra.bottle.tar.gz",
          "sha256": "d81b4668ed5acac3d758bd90b79c01ec12f3ea51186f804941f4d3418c28c72a"
        },
        "x86_64_linux": {
          "url": "https://linuxbrew.bintray.com/bottles/cmus-2.8.0_3.x86_64_linux.bottle.tar.gz",
          "sha256": "013128d9849dc23ee52efcf32241ab3788168acef9a8c509cd9b45e56dbdc227"
        }
      }
    }
  },
  "keg_only": false,
  "bottle_disabled": false,
  "options": [

  ],
  "build_dependencies": [
    "pkg-config"
  ],
  "dependencies": [
    "faad2",
    "ffmpeg",
    "flac",
    "libcue",
    "libogg",
    "libvorbis",
    "mad",
    "mp4v2",
    "opusfile"
  ],
  "recommended_dependencies": [

  ],
  "optional_dependencies": [

  ],
  "uses_from_macos": [

  ],
  "requirements": [

  ],
  "conflicts_with": [

  ],
  "caveats": null,
  "installed": [

  ],
  "linked_keg": null,
  "pinned": false,
  "outdated": false,
  "deprecated": false,
  "disabled": false
}
