{
  "name": "earthly",
  "full_name": "earthly",
  "oldname": null,
  "aliases": [

  ],
  "versioned_formulae": [

  ],
  "desc": "Build automation tool for the post-container era",
  "license": "MPL-2.0",
  "homepage": "https://earthly.dev/",
  "versions": {
    "stable": "0.4.4",
    "head": "HEAD",
    "bottle": true
  },
  "urls": {
    "stable": {
      "url": "https://github.com/earthly/earthly/archive/v0.4.4.tar.gz",
      "tag": null,
      "revision": null
    }
  },
  "revision": 0,
  "version_scheme": 0,
  "bottle": {
    "stable": {
      "rebuild": 0,
      "cellar": ":any_skip_relocation",
      "prefix": "/home/linuxbrew/.linuxbrew",
      "root_url": "https://linuxbrew.bintray.com/bottles",
      "files": {
        "big_sur": {
          "url": "https://linuxbrew.bintray.com/bottles/earthly-0.4.4.big_sur.bottle.tar.gz",
          "sha256": "935725b37ab822ffb7da9d432abe1652edede3715af0d21732f462cc34ebcb2d"
        },
        "arm64_big_sur": {
          "url": "https://linuxbrew.bintray.com/bottles/earthly-0.4.4.arm64_big_sur.bottle.tar.gz",
          "sha256": "594495030b165903fb2f4acbd8712e9eb3f5c41d425206730d38ee136cd6ca1b"
        },
        "catalina": {
          "url": "https://linuxbrew.bintray.com/bottles/earthly-0.4.4.catalina.bottle.tar.gz",
          "sha256": "4a36e325c5c8a46d7e0608d4734d13067e32be5e73bf2ab5844a1f4622067a67"
        },
        "mojave": {
          "url": "https://linuxbrew.bintray.com/bottles/earthly-0.4.4.mojave.bottle.tar.gz",
          "sha256": "6973f902f64db84575a0b4265288e94e72a95676e39f1b24bfab7ceba9adb6e0"
        }
      }
    }
  },
  "keg_only": false,
  "bottle_disabled": false,
  "options": [

  ],
  "build_dependencies": [
    "go"
  ],
  "dependencies": [

  ],
  "recommended_dependencies": [

  ],
  "optional_dependencies": [

  ],
  "uses_from_macos": [

  ],
  "requirements": [

  ],
  "conflicts_with": [

  ],
  "caveats": null,
  "installed": [

  ],
  "linked_keg": null,
  "pinned": false,
  "outdated": false,
  "deprecated": false,
  "deprecation_date": null,
  "deprecation_reason": null,
  "disabled": false,
  "disable_date": null,
  "disable_reason": null
}
