{
  "name": "keydb",
  "full_name": "keydb",
  "oldname": null,
  "aliases": [

  ],
  "versioned_formulae": [

  ],
  "desc": "Multithreaded fork of Redis",
  "homepage": "https://keydb.dev",
  "versions": {
    "stable": "5.3.1",
    "devel": null,
    "head": null,
    "bottle": true
  },
  "urls": {
    "stable": {
      "url": "https://github.com/JohnSully/KeyDB/archive/v5.3.1.tar.gz",
      "tag": null,
      "revision": null
    }
  },
  "revision": 0,
  "version_scheme": 0,
  "bottle": {
    "stable": {
      "rebuild": 0,
      "cellar": ":any_skip_relocation",
      "prefix": "/home/linuxbrew/.linuxbrew",
      "root_url": "https://linuxbrew.bintray.com/bottles",
      "files": {
        "catalina": {
          "url": "https://linuxbrew.bintray.com/bottles/keydb-5.3.1.catalina.bottle.tar.gz",
          "sha256": "3ecbd75e637fc40e8131a35c594b9a028634d55361df0ed83d310b2270c01b5a"
        },
        "mojave": {
          "url": "https://linuxbrew.bintray.com/bottles/keydb-5.3.1.mojave.bottle.tar.gz",
          "sha256": "920ee8aede6c62432d4433fcda41855d4168c039b8e3948c96c38ed98f47d21b"
        },
        "high_sierra": {
          "url": "https://linuxbrew.bintray.com/bottles/keydb-5.3.1.high_sierra.bottle.tar.gz",
          "sha256": "9a4b08c647a79c5e63e0e3d048cb879adf2b6ec2afe223019369486612cc4845"
        }
      }
    }
  },
  "keg_only": false,
  "bottle_disabled": false,
  "options": [

  ],
  "build_dependencies": [

  ],
  "dependencies": [

  ],
  "recommended_dependencies": [

  ],
  "optional_dependencies": [

  ],
  "uses_from_macos": [

  ],
  "requirements": [

  ],
  "conflicts_with": [

  ],
  "caveats": null,
  "installed": [

  ],
  "linked_keg": null,
  "pinned": false,
  "outdated": false
}
