{
  "name": "mono",
  "full_name": "mono",
  "oldname": null,
  "aliases": [

  ],
  "versioned_formulae": [

  ],
  "desc": "Cross platform, open source .NET development framework",
  "homepage": "https://www.mono-project.com/",
  "versions": {
    "stable": "6.8.0.105",
    "devel": null,
    "head": null,
    "bottle": true
  },
  "urls": {
    "stable": {
      "url": "https://download.mono-project.com/sources/mono/mono-6.8.0.105.tar.xz",
      "tag": null,
      "revision": null
    }
  },
  "revision": 0,
  "version_scheme": 0,
  "bottle": {
    "stable": {
      "rebuild": 0,
      "cellar": "/home/linuxbrew/.linuxbrew/Cellar",
      "prefix": "/home/linuxbrew/.linuxbrew",
      "root_url": "https://linuxbrew.bintray.com/bottles",
      "files": {
        "catalina": {
          "url": "https://linuxbrew.bintray.com/bottles/mono-6.8.0.105.catalina.bottle.tar.gz",
          "sha256": "b60510ffecafb1ccd127a8179324a631bfcd23f4e6bbb6aa3ebd94c908ea4c37"
        },
        "mojave": {
          "url": "https://linuxbrew.bintray.com/bottles/mono-6.8.0.105.mojave.bottle.tar.gz",
          "sha256": "406fa52ae8748b58cfecefccc180b1227e98e16de28f7e2442898a6d9d256195"
        },
        "high_sierra": {
          "url": "https://linuxbrew.bintray.com/bottles/mono-6.8.0.105.high_sierra.bottle.tar.gz",
          "sha256": "f7c961d63e628703c661ac3cd2922c1e92c7d78941221acd51439a7fc0d9c331"
        }
      }
    }
  },
  "keg_only": false,
  "bottle_disabled": false,
  "options": [

  ],
  "build_dependencies": [
    "cmake",
    "pkg-config",
    "python@2",
    "unzip"
  ],
  "dependencies": [

  ],
  "recommended_dependencies": [

  ],
  "optional_dependencies": [

  ],
  "uses_from_macos": [

  ],
  "requirements": [
    {
      "name": "macos",
      "cask": null,
      "download": null
    }
  ],
  "conflicts_with": [
    "xsd"
  ],
  "caveats": "To use the assemblies from other formulae you need to set:\n  export MONO_GAC_PREFIX=\"$(brew --prefix)\"\n",
  "installed": [

  ],
  "linked_keg": null,
  "pinned": false,
  "outdated": false
}
