{
  "name": "pnpm",
  "full_name": "pnpm",
  "oldname": null,
  "aliases": [

  ],
  "versioned_formulae": [

  ],
  "desc": "📦🚀 Fast, disk space efficient package manager",
  "homepage": "https://pnpm.js.org",
  "versions": {
    "stable": "4.14.2",
    "devel": null,
    "head": null,
    "bottle": true
  },
  "urls": {
    "stable": {
      "url": "https://registry.npmjs.org/pnpm/-/pnpm-4.14.2.tgz",
      "tag": null,
      "revision": null
    }
  },
  "revision": 0,
  "version_scheme": 0,
  "bottle": {
    "stable": {
      "rebuild": 0,
      "cellar": ":any_skip_relocation",
      "prefix": "/home/linuxbrew/.linuxbrew",
      "root_url": "https://linuxbrew.bintray.com/bottles",
      "files": {
        "catalina": {
          "url": "https://linuxbrew.bintray.com/bottles/pnpm-4.14.2.catalina.bottle.tar.gz",
          "sha256": "9619bc4a88c4c9235357e5d926b81aa444d26b322c16b8675d2d834188ba3ddc"
        },
        "mojave": {
          "url": "https://linuxbrew.bintray.com/bottles/pnpm-4.14.2.mojave.bottle.tar.gz",
          "sha256": "986de8a46fbc3cca2fa97f7ffae6a528d45413b83336384fb72da2918f68c15b"
        },
        "high_sierra": {
          "url": "https://linuxbrew.bintray.com/bottles/pnpm-4.14.2.high_sierra.bottle.tar.gz",
          "sha256": "1922f67940bffb5856765afa4ff70a35fba9ca5d257108ae0b3787e4ea11afa1"
        },
        "x86_64_linux": {
          "url": "https://linuxbrew.bintray.com/bottles/pnpm-4.14.2.x86_64_linux.bottle.tar.gz",
          "sha256": "a01578dd0af3ed1a7bda246450f57dbb8a61614c8dd41e7118ef9345be4a5eb2"
        }
      }
    }
  },
  "keg_only": false,
  "bottle_disabled": false,
  "options": [

  ],
  "build_dependencies": [

  ],
  "dependencies": [
    "node"
  ],
  "recommended_dependencies": [

  ],
  "optional_dependencies": [

  ],
  "uses_from_macos": [

  ],
  "requirements": [

  ],
  "conflicts_with": [

  ],
  "caveats": null,
  "installed": [

  ],
  "linked_keg": null,
  "pinned": false,
  "outdated": false
}
