{
  "name": "bash-git-prompt",
  "full_name": "bash-git-prompt",
  "desc": "Informative, fancy bash prompt for Git users",
  "homepage": "https://github.com/magicmonty/bash-git-prompt",
  "oldname": null,
  "aliases": [

  ],
  "versions": {
    "stable": "2.7.1",
    "bottle": false,
    "devel": null,
    "head": "HEAD"
  },
  "revision": 0,
  "version_scheme": 0,
  "installed": [

  ],
  "linked_keg": null,
  "pinned": false,
  "outdated": false,
  "keg_only": false,
  "dependencies": [

  ],
  "recommended_dependencies": [

  ],
  "optional_dependencies": [

  ],
  "build_dependencies": [

  ],
  "conflicts_with": [

  ],
  "caveats": "You should add the following to your .bashrc (or .bash_profile):\n  if [ -f \"/home/travis/Homebrew/opt/bash-git-prompt/share/gitprompt.sh\" ]; then\n    __GIT_PROMPT_DIR=\"/home/travis/Homebrew/opt/bash-git-prompt/share\"\n    source \"/home/travis/Homebrew/opt/bash-git-prompt/share/gitprompt.sh\"\n  fi\n",
  "requirements": [

  ],
  "options": [

  ],
  "bottle": {
  }
}