{
  "name": "fzy",
  "full_name": "fzy",
  "desc": "Fast, simple fuzzy text selector with an advanced scoring algorithm",
  "homepage": "https://github.com/jhawthorn/fzy",
  "oldname": null,
  "aliases": [

  ],
  "versions": {
    "stable": "0.9",
    "bottle": true,
    "devel": null,
    "head": "HEAD"
  },
  "revision": 0,
  "version_scheme": 0,
  "installed": [

  ],
  "linked_keg": null,
  "pinned": false,
  "outdated": false,
  "keg_only": false,
  "dependencies": [

  ],
  "recommended_dependencies": [

  ],
  "optional_dependencies": [

  ],
  "build_dependencies": [

  ],
  "conflicts_with": [

  ],
  "caveats": null,
  "requirements": [

  ],
  "options": [

  ],
  "bottle": {
    "stable": {
      "rebuild": 0,
      "cellar": ":any_skip_relocation",
      "prefix": "/usr/local",
      "root_url": "https://homebrew.bintray.com/bottles",
      "files": {
        "high_sierra": {
          "url": "https://homebrew.bintray.com/bottles/fzy-0.9.high_sierra.bottle.tar.gz",
          "sha256": "43f5d1a33e63cc16f8a922d3760424f4b2445643ba8260dc31c8cc1f67ad271c"
        },
        "sierra": {
          "url": "https://homebrew.bintray.com/bottles/fzy-0.9.sierra.bottle.tar.gz",
          "sha256": "c1831deb1a5de5c25a48d304dcecd34b87bd9dee67980ea7cbc343289d82a77f"
        },
        "el_capitan": {
          "url": "https://homebrew.bintray.com/bottles/fzy-0.9.el_capitan.bottle.tar.gz",
          "sha256": "88b4a4dd16289fc68a4205911e2a7a1d82ca25aafe1beef9a249c02787c28a98"
        },
        "yosemite": {
          "url": "https://homebrew.bintray.com/bottles/fzy-0.9.yosemite.bottle.tar.gz",
          "sha256": "a72164d23f90277c08c19617c57ddacf7c30dfc9751cc9428d2b1ffd8bd513df"
        }
      }
    }
  }
}