{
  "name": "cubejs-cli",
  "full_name": "cubejs-cli",
  "tap": "homebrew/core",
  "oldname": null,
  "aliases": [

  ],
  "versioned_formulae": [

  ],
  "desc": "Cube.js command-line interface",
  "license": "Apache-2.0",
  "homepage": "https://cube.dev/",
  "versions": {
    "stable": "0.26.6",
    "head": null,
    "bottle": true
  },
  "urls": {
    "stable": {
      "url": "https://registry.npmjs.org/cubejs-cli/-/cubejs-cli-0.26.6.tgz",
      "tag": null,
      "revision": null
    }
  },
  "revision": 0,
  "version_scheme": 0,
  "bottle": {
    "stable": {
      "rebuild": 0,
      "cellar": ":any_skip_relocation",
      "prefix": "/usr/local",
      "root_url": "https://homebrew.bintray.com/bottles",
      "files": {
        "arm64_big_sur": {
          "url": "https://homebrew.bintray.com/bottles/cubejs-cli-0.26.6.arm64_big_sur.bottle.tar.gz",
          "sha256": "f5955e0b5ad403f0196870f4f28c51d2fcc3c5069b918bae5da47b75a58f4deb"
        },
        "big_sur": {
          "url": "https://homebrew.bintray.com/bottles/cubejs-cli-0.26.6.big_sur.bottle.tar.gz",
          "sha256": "975e663775e8837084b5237ce4cf47a72b46514862851930e1e937ddc5fbfa84"
        },
        "catalina": {
          "url": "https://homebrew.bintray.com/bottles/cubejs-cli-0.26.6.catalina.bottle.tar.gz",
          "sha256": "6af79b0e93c3a3d8764a1b48d81a9d1d134a79998d5f508715d7961e62f7f39c"
        },
        "mojave": {
          "url": "https://homebrew.bintray.com/bottles/cubejs-cli-0.26.6.mojave.bottle.tar.gz",
          "sha256": "4abcf0947b9752c65da076b8c52e5a75396cfc1951d8b5fb272aa1fcf386fea1"
        }
      }
    }
  },
  "keg_only": false,
  "bottle_disabled": false,
  "options": [

  ],
  "build_dependencies": [

  ],
  "dependencies": [
    "node"
  ],
  "recommended_dependencies": [

  ],
  "optional_dependencies": [

  ],
  "uses_from_macos": [

  ],
  "requirements": [

  ],
  "conflicts_with": [

  ],
  "caveats": null,
  "installed": [

  ],
  "linked_keg": null,
  "pinned": false,
  "outdated": false,
  "deprecated": false,
  "deprecation_date": null,
  "deprecation_reason": null,
  "disabled": false,
  "disable_date": null,
  "disable_reason": null
}
