{
  "name": "fontforge",
  "full_name": "fontforge",
  "oldname": null,
  "aliases": [

  ],
  "versioned_formulae": [

  ],
  "desc": "Command-line outline and bitmap font editor/converter",
  "homepage": "https://fontforge.github.io",
  "versions": {
    "stable": "20170731",
    "devel": null,
    "head": null,
    "bottle": true
  },
  "revision": 3,
  "version_scheme": 0,
  "bottle": {
    "stable": {
      "rebuild": 1,
      "cellar": "/home/linuxbrew/.linuxbrew/Cellar",
      "prefix": "/home/linuxbrew/.linuxbrew",
      "root_url": "https://linuxbrew.bintray.com/bottles",
      "files": {
        "mojave": {
          "url": "https://linuxbrew.bintray.com/bottles/fontforge-20170731_3.mojave.bottle.1.tar.gz",
          "sha256": "7917392b435917468ce7f8e4c31822ba376d901cc9303ab354c44ef8155fad49"
        },
        "high_sierra": {
          "url": "https://linuxbrew.bintray.com/bottles/fontforge-20170731_3.high_sierra.bottle.1.tar.gz",
          "sha256": "5a04540e69d56213fb104a968ad9ce2bc5c2ca152d5c3e0ecfccbd93981f80dc"
        },
        "sierra": {
          "url": "https://linuxbrew.bintray.com/bottles/fontforge-20170731_3.sierra.bottle.1.tar.gz",
          "sha256": "7c4e3def1ac5f5b374e773d6dd7bda60b09eb304a19c6b231a292125d4d14915"
        }
      }
    }
  },
  "keg_only": false,
  "options": [
    {
      "option": "--with-extra-tools",
      "description": "Build with additional font tools"
    }
  ],
  "build_dependencies": [
    "pkg-config"
  ],
  "dependencies": [
    "cairo",
    "fontconfig",
    "gettext",
    "giflib",
    "jpeg",
    "libpng",
    "libspiro",
    "libtiff",
    "libtool",
    "libuninameslist",
    "pango",
    "python@2"
  ],
  "recommended_dependencies": [

  ],
  "optional_dependencies": [

  ],
  "requirements": [

  ],
  "conflicts_with": [

  ],
  "caveats": "This formula only installs the command line utilities.\n\nFontForge.app can be downloaded directly from the website:\n  https://fontforge.github.io\n\nAlternatively, install with Homebrew Cask:\n  brew cask install fontforge\n",
  "installed": [

  ],
  "linked_keg": null,
  "pinned": false,
  "outdated": false
}