{
  "name": "hub",
  "full_name": "hub",
  "oldname": null,
  "aliases": [

  ],
  "versioned_formulae": [

  ],
  "desc": "Add GitHub support to git on the command-line",
  "homepage": "https://hub.github.com/",
  "versions": {
    "stable": "2.9.0",
    "devel": null,
    "head": "HEAD",
    "bottle": true
  },
  "revision": 0,
  "version_scheme": 0,
  "bottle": {
    "stable": {
      "rebuild": 0,
      "cellar": ":any_skip_relocation",
      "prefix": "/usr/local",
      "root_url": "https://homebrew.bintray.com/bottles",
      "files": {
        "mojave": {
          "url": "https://homebrew.bintray.com/bottles/hub-2.9.0.mojave.bottle.tar.gz",
          "sha256": "7d9c176f0d0403de37e8163bcb70b124a33087d073a150f74cdb06f14d7a989b"
        },
        "high_sierra": {
          "url": "https://homebrew.bintray.com/bottles/hub-2.9.0.high_sierra.bottle.tar.gz",
          "sha256": "bd033644c86186e01c9fe00f840dd01d5258c4ffca3522fb6115052f4022879a"
        },
        "sierra": {
          "url": "https://homebrew.bintray.com/bottles/hub-2.9.0.sierra.bottle.tar.gz",
          "sha256": "f187d6811693f665d747c14f9aeaecab31d7243691c4070640eaa1ea58f6ef98"
        }
      }
    }
  },
  "keg_only": false,
  "options": [

  ],
  "build_dependencies": [
    "go"
  ],
  "dependencies": [

  ],
  "recommended_dependencies": [

  ],
  "optional_dependencies": [

  ],
  "requirements": [

  ],
  "conflicts_with": [

  ],
  "caveats": null,
  "installed": [

  ],
  "linked_keg": null,
  "pinned": false,
  "outdated": false
}