{
  "name": "macvim",
  "full_name": "macvim",
  "oldname": null,
  "aliases": [

  ],
  "versioned_formulae": [

  ],
  "desc": "GUI for vim, made for macOS",
  "homepage": "https://github.com/macvim-dev/macvim",
  "versions": {
    "stable": "8.1-149",
    "devel": null,
    "head": "HEAD",
    "bottle": true
  },
  "revision": 1,
  "version_scheme": 0,
  "bottle": {
    "stable": {
      "rebuild": 0,
      "cellar": "/usr/local/Cellar",
      "prefix": "/usr/local",
      "root_url": "https://homebrew.bintray.com/bottles",
      "files": {
        "high_sierra": {
          "url": "https://homebrew.bintray.com/bottles/macvim-8.1-149_1.high_sierra.bottle.tar.gz",
          "sha256": "de3b99d6cbfee13408248bd7f42b146cb8f2b9d92aa42a90544d6fd82d3d6f0f"
        },
        "sierra": {
          "url": "https://homebrew.bintray.com/bottles/macvim-8.1-149_1.sierra.bottle.tar.gz",
          "sha256": "31a9ed55a26b2b5bb6ec5c21aa13dc1e81d4661c4aac14349eac785315830de5"
        },
        "el_capitan": {
          "url": "https://homebrew.bintray.com/bottles/macvim-8.1-149_1.el_capitan.bottle.tar.gz",
          "sha256": "7b9d75f6145bb2f4a9eabb3bc307be19e31d3d4201429f908b449725777831db"
        }
      }
    }
  },
  "keg_only": false,
  "options": [
    {
      "option": "--with-override-system-vim",
      "description": "Override system vim"
    },
    {
      "option": "--without-cscope",
      "description": "Build without cscope support"
    },
    {
      "option": "--without-python",
      "description": "Build without python support"
    },
    {
      "option": "--with-lua",
      "description": "Build with lua support"
    },
    {
      "option": "--with-luajit",
      "description": "Build with luajit support"
    },
    {
      "option": "--with-python@2",
      "description": "Build with python@2 support"
    }
  ],
  "build_dependencies": [

  ],
  "dependencies": [

  ],
  "recommended_dependencies": [
    "cscope",
    "python"
  ],
  "optional_dependencies": [
    "lua",
    "luajit",
    "python@2"
  ],
  "requirements": [
    {
      "name": "xcode",
      "cask": null,
      "download": null
    }
  ],
  "conflicts_with": [

  ],
  "caveats": null,
  "installed": [

  ],
  "linked_keg": null,
  "pinned": false,
  "outdated": false
}