{
  "name": "pypy",
  "full_name": "pypy",
  "oldname": null,
  "aliases": [

  ],
  "versioned_formulae": [

  ],
  "desc": "Highly performant implementation of Python 2 in Python",
  "homepage": "https://pypy.org/",
  "versions": {
    "stable": "7.3.0",
    "devel": null,
    "head": "HEAD",
    "bottle": true
  },
  "revision": 0,
  "version_scheme": 0,
  "bottle": {
    "stable": {
      "rebuild": 0,
      "cellar": ":any",
      "prefix": "/usr/local",
      "root_url": "https://homebrew.bintray.com/bottles",
      "files": {
        "catalina": {
          "url": "https://homebrew.bintray.com/bottles/pypy-7.3.0.catalina.bottle.tar.gz",
          "sha256": "50da6ab456d0fdacb2c341d22ec076a71b17604d2e8064816533351da740dd9a"
        },
        "mojave": {
          "url": "https://homebrew.bintray.com/bottles/pypy-7.3.0.mojave.bottle.tar.gz",
          "sha256": "a627136e148de7908a716d249b7364e041a39ec3d9bccf5f17ce019b670bfc05"
        },
        "high_sierra": {
          "url": "https://homebrew.bintray.com/bottles/pypy-7.3.0.high_sierra.bottle.tar.gz",
          "sha256": "c1fb435418a17ffc1f0c26284ff702fe350df1de28501d37f161bdd5182003dc"
        }
      }
    }
  },
  "keg_only": false,
  "bottle_disabled": false,
  "options": [

  ],
  "build_dependencies": [
    "pkg-config"
  ],
  "dependencies": [
    "gdbm",
    "libffi",
    "openssl@1.1",
    "sqlite",
    "tcl-tk"
  ],
  "recommended_dependencies": [

  ],
  "optional_dependencies": [

  ],
  "uses_from_macos": [

  ],
  "requirements": [
    {
      "name": "arch",
      "cask": null,
      "download": null
    }
  ],
  "conflicts_with": [

  ],
  "caveats": "A \"distutils.cfg\" has been written to:\n  $(brew --prefix)/Cellar/pypy/7.3.0/libexec/lib-python/2.7/distutils\nspecifying the install-scripts folder as:\n  $(brew --prefix)/share/pypy\n\nIf you install Python packages via \"pypy setup.py install\", easy_install_pypy,\nor pip_pypy, any provided scripts will go into the install-scripts folder\nabove, so you may want to add it to your PATH *after* $(brew --prefix)/bin\nso you don't overwrite tools from CPython.\n\nSetuptools and pip have been installed, so you can use easy_install_pypy and\npip_pypy.\nTo update setuptools and pip between pypy releases, run:\n    pip_pypy install --upgrade pip setuptools\n\nSee: https://docs.brew.sh/Homebrew-and-Python\n",
  "installed": [

  ],
  "linked_keg": null,
  "pinned": false,
  "outdated": false
}
