{
  "name": "simgrid",
  "full_name": "simgrid",
  "tap": "homebrew/core",
  "oldname": null,
  "aliases": [

  ],
  "versioned_formulae": [

  ],
  "desc": "Studies behavior of large-scale distributed systems",
  "license": null,
  "homepage": "https://simgrid.org/",
  "versions": {
    "stable": "3.28",
    "head": null,
    "bottle": true
  },
  "urls": {
    "stable": {
      "url": "https://framagit.org/simgrid/simgrid/uploads/5d171dff8b988c639fe52baa24952a2c/simgrid-3.28.tar.gz",
      "tag": null,
      "revision": null
    }
  },
  "revision": 0,
  "version_scheme": 0,
  "bottle": {
    "stable": {
      "rebuild": 0,
      "root_url": "https://ghcr.io/v2/homebrew/core",
      "files": {
        "arm64_big_sur": {
          "cellar": "/opt/homebrew/Cellar",
          "url": "https://ghcr.io/v2/homebrew/core/simgrid/blobs/sha256:71d9b098d5fd0039bbc7005555d0f1abbc1af8d816a8946629f55046a1b47615",
          "sha256": "71d9b098d5fd0039bbc7005555d0f1abbc1af8d816a8946629f55046a1b47615"
        },
        "big_sur": {
          "cellar": "/usr/local/Cellar",
          "url": "https://ghcr.io/v2/homebrew/core/simgrid/blobs/sha256:def3ab73795d0c11ce112ad3fb3abcd325815bda779637961c6a8b4c43e1ef06",
          "sha256": "def3ab73795d0c11ce112ad3fb3abcd325815bda779637961c6a8b4c43e1ef06"
        },
        "catalina": {
          "cellar": "/usr/local/Cellar",
          "url": "https://ghcr.io/v2/homebrew/core/simgrid/blobs/sha256:ee5bc62941284de0277bc1ea39467ea06c4cb611d8144a689c2060a1b2c3588e",
          "sha256": "ee5bc62941284de0277bc1ea39467ea06c4cb611d8144a689c2060a1b2c3588e"
        },
        "mojave": {
          "cellar": "/usr/local/Cellar",
          "url": "https://ghcr.io/v2/homebrew/core/simgrid/blobs/sha256:b7c787533f73e4a8fcfa07f50171879e949ffc1d615c680ccb98bd985e14de60",
          "sha256": "b7c787533f73e4a8fcfa07f50171879e949ffc1d615c680ccb98bd985e14de60"
        }
      }
    }
  },
  "keg_only": false,
  "bottle_disabled": false,
  "options": [

  ],
  "build_dependencies": [
    "cmake",
    "doxygen"
  ],
  "dependencies": [
    "boost",
    "graphviz",
    "pcre",
    "python@3.9"
  ],
  "recommended_dependencies": [

  ],
  "optional_dependencies": [

  ],
  "uses_from_macos": [

  ],
  "requirements": [

  ],
  "conflicts_with": [

  ],
  "caveats": null,
  "installed": [

  ],
  "linked_keg": null,
  "pinned": false,
  "outdated": false,
  "deprecated": false,
  "deprecation_date": null,
  "deprecation_reason": null,
  "disabled": false,
  "disable_date": null,
  "disable_reason": null
}
