{
  "name": "wasmer",
  "full_name": "wasmer",
  "oldname": null,
  "aliases": [

  ],
  "versioned_formulae": [

  ],
  "desc": "🚀 The Universal WebAssembly Runtime",
  "homepage": "https://wasmer.io",
  "versions": {
    "stable": "0.16.0",
    "devel": null,
    "head": "HEAD",
    "bottle": true
  },
  "urls": {
    "stable": {
      "url": "https://github.com/wasmerio/wasmer/archive/0.16.0.tar.gz",
      "tag": null,
      "revision": null
    }
  },
  "revision": 0,
  "version_scheme": 0,
  "bottle": {
    "stable": {
      "rebuild": 0,
      "cellar": ":any_skip_relocation",
      "prefix": "/usr/local",
      "root_url": "https://homebrew.bintray.com/bottles",
      "files": {
        "catalina": {
          "url": "https://homebrew.bintray.com/bottles/wasmer-0.16.0.catalina.bottle.tar.gz",
          "sha256": "391dec3e05dd8fdd8d5dbe602b6a2a9186abcb024bf3f581e83bb5b235c5333a"
        },
        "mojave": {
          "url": "https://homebrew.bintray.com/bottles/wasmer-0.16.0.mojave.bottle.tar.gz",
          "sha256": "cf6118fee3b8247c3e55b885a4b0eff21d256d663cfe09ca9682b66e3a0f6dd6"
        },
        "high_sierra": {
          "url": "https://homebrew.bintray.com/bottles/wasmer-0.16.0.high_sierra.bottle.tar.gz",
          "sha256": "bf72871eacaf031eca8d0508b462ddb4209f482f2a3570eeb0c9eeab50833b37"
        }
      }
    }
  },
  "keg_only": false,
  "bottle_disabled": false,
  "options": [

  ],
  "build_dependencies": [
    "cmake",
    "rust",
    "wabt"
  ],
  "dependencies": [

  ],
  "recommended_dependencies": [

  ],
  "optional_dependencies": [

  ],
  "uses_from_macos": [

  ],
  "requirements": [

  ],
  "conflicts_with": [

  ],
  "caveats": null,
  "installed": [

  ],
  "linked_keg": null,
  "pinned": false,
  "outdated": false
}
