{
  "name": "ydiff",
  "full_name": "ydiff",
  "oldname": "cdiff",
  "aliases": [

  ],
  "versioned_formulae": [

  ],
  "desc": "View colored diff with side by side and auto pager support",
  "homepage": "https://github.com/ymattw/ydiff",
  "versions": {
    "stable": "1.1",
    "devel": null,
    "head": null,
    "bottle": false
  },
  "revision": 0,
  "version_scheme": 0,
  "bottle": {
  },
  "keg_only": false,
  "bottle_disabled": true,
  "options": [

  ],
  "build_dependencies": [

  ],
  "dependencies": [

  ],
  "recommended_dependencies": [

  ],
  "optional_dependencies": [

  ],
  "uses_from_macos": [

  ],
  "requirements": [

  ],
  "conflicts_with": [

  ],
  "caveats": null,
  "installed": [

  ],
  "linked_keg": null,
  "pinned": false,
  "outdated": false
}
