{
  "token": "axure-rp",
  "full_token": "axure-rp",
  "tap": "homebrew/cask",
  "name": [
    "Axure RP"
  ],
  "desc": "Planning and prototyping tool for developers",
  "homepage": "https://www.axure.com/",
  "url": "https://axure.cachefly.net/versions/10-0/AxureRP-Setup-3851.dmg",
  "appcast": null,
  "version": "10.0.0.3851",
  "versions": {
  },
  "installed": null,
  "outdated": false,
  "sha256": "f94d284b0f9144fa26264807d5831486b437db3cbb96c8aec4c92126beb0b5aa",
  "artifacts": [
    [
      "Axure RP 10.app"
    ],
    {
      "trash": [
        "~/Library/Application Support/com.apple.sharedfilelist/com.apple.LSSharedFileList.ApplicationRecentDocuments/com.axure.axurerp10.sfl*",
        "~/Library/Preferences/com.axure.AxureRP10.plist",
        "~/Library/Saved Application State/com.axure.AxureRP10.savedState"
      ],
      "signal": {
      }
    }
  ],
  "caveats": null,
  "depends_on": {
  },
  "conflicts_with": null,
  "container": null,
  "auto_updates": null
}
