{
  "token": "busycontacts",
  "full_token": "busycontacts",
  "tap": "homebrew/cask",
  "name": [
    "BusyContacts"
  ],
  "desc": "Contact manager focusing on efficiency",
  "homepage": "https://www.busymac.com/busycontacts/index.html",
  "url": "https://7e968b6ce8a839f034d9-23cfb9eddcb7b94cb43ba95f95a76900.ssl.cf1.rackcdn.com/bct-2022.4.5-2022-12-30-14-11.zip",
  "appcast": null,
  "version": "2022.4.5,2022-12-30-14-11",
  "versions": {
  },
  "installed": null,
  "outdated": false,
  "sha256": "166a9956f18463b55cf42c1cef3bec1ba1ca4e859793b42a9ae58b8d9dfa084d",
  "artifacts": [
    {
      "uninstall": [
        {
          "pkgutil": "com.busymac.busycontacts.pkg",
          "quit": "com.busymac.busycontacts",
          "signal": [
            "KILL",
            "com.busymac.busycontacts"
          ]
        }
      ]
    },
    {
      "pkg": [
        "BusyContacts Installer.pkg"
      ]
    }
  ],
  "caveats": null,
  "depends_on": {
  },
  "conflicts_with": null,
  "container": null,
  "auto_updates": true,
  "variations": {
  }
}
