{
  "token": "freeyourmusic",
  "name": [
    "FreeYourMusic⁩"
  ],
  "homepage": "https://freeyourmusic.com/",
  "url": "https://dzqeytqqx888.cloudfront.net/FreeYourMusic-5.4.2.dmg",
  "appcast": "https://stamp-live.s3.amazonaws.com/latest-mac.yml",
  "version": "5.4.2",
  "sha256": "f1103e639b75430fb255180b5b61142efc3febe96aa0426d048e3b8f48800f46",
  "artifacts": [
    [
      "FreeYourMusic.app"
    ]
  ],
  "caveats": null,
  "depends_on": {
  },
  "conflicts_with": null,
  "container": null,
  "auto_updates": null
}
