{
  "token": "hook",
  "full_token": "hook",
  "tap": "homebrew/cask",
  "name": [
    "Hook"
  ],
  "desc": "Link and retrieve key information",
  "homepage": "https://hookproductivity.com/",
  "url": "https://hookproductivity.com/wp-content/uploads/2022/06/Hook-productivity-app-3.6.1.dmg_.zip",
  "appcast": null,
  "version": "3.6.1,2022.06",
  "versions": {
  },
  "installed": null,
  "outdated": false,
  "sha256": "f4c08856e64e1dd6eb03abad30b7a4dcba81f3391e8399fbeb28e45bf2f90412",
  "artifacts": [
    {
      "launchctl": "com.cogsciapps.hookautolaunchhelper",
      "quit": "com.cogsciapps.hook",
      "signal": {
      }
    },
    [
      "Hook.app"
    ],
    {
      "trash": [
        "~/Library/Caches/com.cogsciapps.hook",
        "~/Library/Logs/com.cogsciapps.hook",
        "~/Library/Preferences/com.cogsciapps.hook.plist"
      ],
      "signal": {
      }
    }
  ],
  "caveats": null,
  "depends_on": {
  },
  "conflicts_with": null,
  "container": null,
  "auto_updates": true,
  "variations": {
  }
}
