{
  "token": "insomnia",
  "name": [
    "Insomnia"
  ],
  "homepage": "https://insomnia.rest/",
  "url": "https://github.com/getinsomnia/insomnia/releases/download/v7.0.3/Insomnia-7.0.3.dmg",
  "appcast": "https://insomnia.rest/changelog/index.xml",
  "version": "7.0.3",
  "sha256": "0e2f90e6a761fe273eb978e00f55b13a2c7cd3a9816816136dccb6f7bde46518",
  "artifacts": [
    [
      "Insomnia.app"
    ],
    {
      "trash": [
        "~/Library/Application Support/Insomnia",
        "~/Library/Caches/com.insomnia.app",
        "~/Library/Caches/com.insomnia.app.ShipIt",
        "~/Library/Cookies/com.insomnia.app.binarycookies",
        "~/Library/Preferences/com.insomnia.app.helper.plist",
        "~/Library/Preferences/com.insomnia.app.plist",
        "~/Library/Saved Application State/com.insomnia.app.savedState"
      ],
      "signal": {
      }
    }
  ],
  "caveats": null,
  "depends_on": {
  },
  "conflicts_with": null,
  "container": null,
  "auto_updates": true
}
