{
  "token": "keeweb",
  "name": [
    "KeeWeb"
  ],
  "homepage": "https://keeweb.info/",
  "url": "https://github.com/keeweb/keeweb/releases/download/v1.13.3/KeeWeb-1.13.3.mac.dmg",
  "appcast": "https://github.com/keeweb/keeweb/releases.atom",
  "version": "1.13.3",
  "sha256": "7584a2eb1fb7ab4cc26932d06c6398c65abe3ac150101cd6d6302dffd3afdceb",
  "artifacts": [
    "uninstall_preflight (Preflight Block)",
    [
      "KeeWeb.app"
    ]
  ],
  "caveats": null,
  "depends_on": {
  },
  "conflicts_with": null,
  "container": null,
  "auto_updates": true
}
