{
  "token": "lark",
  "full_token": "lark",
  "tap": "homebrew/cask",
  "name": [
    "Lark"
  ],
  "desc": "Project management software",
  "homepage": "https://www.larksuite.com/",
  "url": "https://sf16-va.larksuitecdn.com/obj/lark-artifact-storage/ad89b4/Lark-darwin_x64-5.17.10-signed.dmg",
  "appcast": null,
  "version": "5.17.10,ad89b4",
  "versions": {
  },
  "installed": null,
  "outdated": false,
  "sha256": "835758f5b674297514252e7db420ff585b2f7df9e9b09eaff31243d2e9e32b70",
  "artifacts": [
    {
      "app": [
        "Lark.app"
      ]
    },
    {
      "zap": [
        {
          "trash": [
            "~/Library/Caches/com.bytedance.lark.helper",
            "~/Library/Preferences/com.bytedance.lark.helper.plist",
            "~/Library/Caches/com.electron.lark.helper",
            "~/Library/Preferences/com.electron.lark.helper.plist",
            "~/Library/Caches/com.electron.lark",
            "~/Library/Saved Application State/com.electron.lark.savedState"
          ]
        }
      ]
    }
  ],
  "caveats": null,
  "depends_on": {
  },
  "conflicts_with": null,
  "container": null,
  "auto_updates": true,
  "variations": {
    "arm64_ventura": {
      "url": "https://sf16-va.larksuitecdn.com/obj/lark-artifact-storage/2ed2be/Lark-darwin_arm64-5.17.10-signed.dmg",
      "version": "5.17.10,2ed2be",
      "sha256": "7f954e8267cbb0c8b205b3aebe0b5c3a1a4c6c1f75919516ffb8d2a9af415740"
    },
    "arm64_monterey": {
      "url": "https://sf16-va.larksuitecdn.com/obj/lark-artifact-storage/2ed2be/Lark-darwin_arm64-5.17.10-signed.dmg",
      "version": "5.17.10,2ed2be",
      "sha256": "7f954e8267cbb0c8b205b3aebe0b5c3a1a4c6c1f75919516ffb8d2a9af415740"
    },
    "arm64_big_sur": {
      "url": "https://sf16-va.larksuitecdn.com/obj/lark-artifact-storage/2ed2be/Lark-darwin_arm64-5.17.10-signed.dmg",
      "version": "5.17.10,2ed2be",
      "sha256": "7f954e8267cbb0c8b205b3aebe0b5c3a1a4c6c1f75919516ffb8d2a9af415740"
    }
  }
}
