{
  "token": "manico",
  "full_token": "manico",
  "tap": "homebrew/cask",
  "name": [
    "Manico"
  ],
  "desc": "App launcher and switcher",
  "homepage": "https://manico.im/",
  "url": "https://manico.im/api/release_manager/downloads/im.manico.Manico/430.zip",
  "appcast": null,
  "version": "3.0.3,430",
  "versions": {
  },
  "installed": null,
  "outdated": false,
  "sha256": "522cba47fdcbdf908c4d112b010778b41679e13d528730a91164d01015534ec9",
  "artifacts": [
    [
      "Manico.app"
    ],
    {
      "trash": "~/Library/Containers/im.manico.Manico",
      "signal": {
      }
    }
  ],
  "caveats": null,
  "depends_on": {
    "macos": {
      ">=": [
        "10.14"
      ]
    }
  },
  "conflicts_with": null,
  "container": null,
  "auto_updates": null
}
