{
  "name": [
    "Mini Program Studio",
    "小程序开发者工具"
  ],
  "homepage": "https://open.alipay.com/channel/miniIndex.htm",
  "url": "https://gw.alipayobjects.com/os/volans-demo/05647aea-1185-4a78-9db5-02989f0d6414/0.40.4/MiniProgramStudio-0.40.4.pkg",
  "appcast": null,
  "version": "0.40.4,05647aea-1185-4a78-9db5-02989f0d6414",
  "sha256": "2e8ca3944327c730a50819f8b1be62a4fa9d7cf1d0483c202db3eef03ba50a62",
  "artifacts": [
    {
      "pkgutil": "com.ant.miniprogram",
      "signal": {
      }
    },
    "MiniProgramStudio-0.40.4.pkg (Pkg)",
    {
      "trash": [
        "~/Library/Application Support/小程序开发者工具",
        "~/Library/Preferences/com.ant.tiny.helper.plist",
        "~/Library/Preferences/com.ant.miniprogram.helper.plist",
        "~/Library/Preferences/com.ant.miniprogram.plist",
        "~/Library/Preferences/com.ant.miniprogram.plist",
        "~/Library/Saved Application State/com.ant.miniprogram.savedState",
        "~/Library/Saved Application State/com.ant.tiny.savedState"
      ],
      "signal": {
      }
    }
  ],
  "caveats": "",
  "depends_on": {
  },
  "conflicts_with": null,
  "container": null,
  "auto_updates": null
}
