{
  "token": "mongodb-compass",
  "full_token": "mongodb-compass",
  "tap": "homebrew/cask",
  "name": [
    "MongoDB Compass"
  ],
  "desc": "Explore and manipulate your MongoDB data",
  "homepage": "https://www.mongodb.com/products/compass",
  "url": "https://downloads.mongodb.com/compass/mongodb-compass-1.32.2-darwin-x64.dmg",
  "appcast": null,
  "version": "1.32.2",
  "versions": {
  },
  "installed": null,
  "outdated": false,
  "sha256": "919862931f30dacbf9518818964b8027f737a2b56e2cb75e53deef9acd839230",
  "artifacts": [
    [
      "MongoDB Compass.app"
    ],
    {
      "trash": [
        "~/Library/Application Support/com.apple.sharedfilelist/com.apple.LSSharedFileList.ApplicationRecentDocuments/com.mongodb.compass.sfl*",
        "~/Library/Application Support/MongoDB Compass",
        "~/Library/Caches/MongoDB Compass/",
        "~/Library/Preferences/com.mongodb.compass.plist",
        "~/Library/Saved Application State/com.mongodb.compass.savedState"
      ],
      "signal": {
      }
    }
  ],
  "caveats": null,
  "depends_on": {
  },
  "conflicts_with": null,
  "container": null,
  "auto_updates": null
}
