{
  "token": "mountain-duck",
  "name": [
    "Mountain Duck"
  ],
  "homepage": "https://mountainduck.io/",
  "url": "https://dist.mountainduck.io/Mountain%20Duck-3.3.6.15539.zip",
  "appcast": "https://version.mountainduck.io/3/macos/changelog.rss",
  "version": "3.3.6.15539",
  "sha256": "56744543ef30538faeebda84120940ad43575e670b4953f470cf23ff875ff039",
  "artifacts": [
    [
      "Mountain Duck.app"
    ]
  ],
  "caveats": null,
  "depends_on": {
  },
  "conflicts_with": null,
  "container": null,
  "auto_updates": null
}
