{
  "token": "opera",
  "full_token": "opera",
  "tap": "homebrew/cask",
  "name": [
    "Opera"
  ],
  "desc": "Web browser",
  "homepage": "https://www.opera.com/",
  "url": "https://get.geo.opera.com/pub/opera/desktop/87.0.4390.25/mac/Opera_87.0.4390.25_Setup.dmg",
  "appcast": null,
  "version": "87.0.4390.25",
  "versions": {
  },
  "installed": null,
  "outdated": false,
  "sha256": "caf29dd596d147d1c9b6ff61c93ff88b0278717f74f8be843c970eee10bf4c8b",
  "artifacts": [
    [
      "Opera.app"
    ],
    {
      "trash": [
        "~/Library/Application Support/com.operasoftware.Opera/",
        "~/Library/Preferences/com.operasoftware.Opera.plist"
      ],
      "signal": {
      }
    }
  ],
  "caveats": null,
  "depends_on": {
  },
  "conflicts_with": null,
  "container": null,
  "auto_updates": true
}
