{
  "token": "opera",
  "full_token": "opera",
  "tap": "homebrew/cask",
  "name": [
    "Opera"
  ],
  "desc": "Web browser",
  "homepage": "https://www.opera.com/",
  "url": "https://get.geo.opera.com/pub/opera/desktop/75.0.3969.218/mac/Opera_75.0.3969.218_Setup.dmg",
  "appcast": null,
  "version": "75.0.3969.218",
  "installed": null,
  "outdated": false,
  "sha256": "547f22977bd744941f0d68175853af0aaee987e209ae29a096c1799fddf3ff12",
  "artifacts": [
    [
      "Opera.app"
    ],
    {
      "trash": [
        "~/Library/Preferences/com.operasoftware.Opera.plist",
        "~/Library/Application Support/com.operasoftware.Opera/"
      ],
      "signal": {
      }
    }
  ],
  "caveats": null,
  "depends_on": {
  },
  "conflicts_with": null,
  "container": null,
  "auto_updates": true
}
