{
  "token": "publii",
  "full_token": "publii",
  "tap": "homebrew/cask",
  "name": [
    "Publii"
  ],
  "desc": "Static website generator",
  "homepage": "https://getpublii.com/",
  "url": "https://cdn.getpublii.com/Publii-0.38.2.dmg",
  "appcast": null,
  "version": "0.38.2",
  "installed": null,
  "outdated": false,
  "sha256": "2c66402946c96ac14c805c4738775208fbde257185427355f17061298082a07c",
  "artifacts": [
    [
      "Publii.app"
    ],
    {
      "trash": [
        "~/Documents/Publii",
        "~/Library/Application Support/Publii",
        "~/Library/Logs/Publii",
        "~/Library/Preferences/com.tidycustoms.publii.plist"
      ],
      "signal": {
      }
    }
  ],
  "caveats": null,
  "depends_on": {
  },
  "conflicts_with": null,
  "container": null,
  "auto_updates": null
}
