{
  "token": "silentknight",
  "name": [
    "SilentKnight"
  ],
  "desc": "Automatically checks computer's security",
  "homepage": "https://eclecticlight.co/lockrattler-systhist/",
  "url": "https://eclecticlightdotcom.files.wordpress.com/2020/11/silentknight112.zip",
  "appcast": "https://www.macupdater.net/cgi-bin/extract_text/extract_text_split_easy.cgi?url=https://raw.githubusercontent.com/hoakleyelc/updates/master/eclecticapps.plist&splitter_1=SilentKnight&index_1=1&splitter_2=Version&index_2=1&splitter_3=dict&index_3=0",
  "version": "1.12,2020.11",
  "sha256": "3ce5c42606d6237b9c8b036da73a9842118f0929d478f86f458f07aa8e2dc384",
  "artifacts": [
    [
      "silentknight112/SilentKnight.app"
    ],
    {
      "trash": [
        "~/Library/Caches/co.eclecticlight.SilentKnight",
        "~/Library/Preferences/co.eclecticlight.SilentKnight.plist",
        "~/Library/Saved Application State/co.eclecticlight.SilentKnight.savedState"
      ],
      "signal": {
      }
    }
  ],
  "caveats": null,
  "depends_on": {
    "macos": {
      ">=": [
        "10.11"
      ]
    }
  },
  "conflicts_with": null,
  "container": null,
  "auto_updates": null
}
