{
  "token": "thedesk",
  "name": [
    "TheDesk"
  ],
  "desc": "Mastodon/Misskey Client for PC",
  "homepage": "https://thedesk.top/",
  "url": "https://github.com/cutls/TheDesk/releases/download/v22.0.0/TheDesk-22.0.0.dmg",
  "appcast": "https://github.com/cutls/TheDesk/releases.atom",
  "version": "22.0.0",
  "sha256": "0b8de299576bbb0f80382a22b7ab35b27e8fa1f722abb4b8f268e4d6670baeca",
  "artifacts": [
    [
      "TheDesk.app"
    ]
  ],
  "caveats": null,
  "depends_on": {
  },
  "conflicts_with": null,
  "container": null,
  "auto_updates": null
}
