{
  "token": "universal-media-server",
  "full_token": "universal-media-server",
  "tap": "homebrew/cask",
  "name": [
    "Universal Media Server"
  ],
  "desc": "Media server supporting DLNA, UPnP and HTTP(S)",
  "homepage": "https://www.universalmediaserver.com/",
  "url": "https://github.com/UniversalMediaServer/UniversalMediaServer/releases/download/10.12.0/UMS-10.12.0.dmg",
  "appcast": null,
  "version": "10.12.0",
  "versions": {
  },
  "installed": null,
  "outdated": false,
  "sha256": "bc04df210e6d5f23d891c2188ccb331714ca48f337af0cac96a1da17ba1ff79d",
  "artifacts": [
    [
      "Universal Media Server.app"
    ],
    {
      "trash": "~/Library/Application Support/UMS/",
      "signal": {
      }
    }
  ],
  "caveats": null,
  "depends_on": {
    "macos": {
      ">=": [
        "10.15"
      ]
    }
  },
  "conflicts_with": null,
  "container": null,
  "auto_updates": null
}
